{"gender":"Female","age":24,"nationality":"JM","familiarity":"Sometimes","englishLevel":"Native","dominantHand":"Right","swipeHand":"Right","swipeFinger":"Thumb","screenWidth":360,"screenHeight":640,"devicePixelRatio":2,"maxTouchPoints":5,"platform":"Linux armv8l","vendor":"Google Inc.","referal":"https://www.typingtest.com/result.html?acc=64&nwpm=14&gwpm=22&ncpm=74&gcpm=114&dur=60&time=60&chksum=4749&unit=wpm&kh=998&td=null&err=8&hits=114&textfile=oz.txt","language":"en-US,en;q=0.9","userAgent":"Mozilla/5.0 (Linux; Android 7.0; SAMSUNG SM-S737TL) AppleWebKit/537.36 (KHTML, like Gecko) SamsungBrowser/11.1 Chrome/75.0.3770.143 Mobile Safari/537.36","timestamp":1583957738}
