{"gender":"Female","age":18,"nationality":"IN","familiarity":"Sometimes","englishLevel":"Intermediate","dominantHand":"Right","swipeHand":"Right","swipeFinger":"Index","screenWidth":360,"screenHeight":780,"devicePixelRatio":3,"maxTouchPoints":5,"platform":"Linux armv8l","vendor":"Google Inc.","referal":"https://www.typingtest.com/result.html?acc=84&nwpm=10&gwpm=12&ncpm=53&gcpm=63&dur=300&time=300&chksum=4465&unit=wpm&kh=998&td=null&err=10&hits=315&textfile=baseball.txt","language":"en-KE,en-US;q=0.9,en;q=0.8","userAgent":"Mozilla/5.0 (Linux; Android 9; CPH1823) AppleWebKit/537.36 (KHTML, like Gecko) Chrome/79.0.3945.136 Mobile Safari/537.36","timestamp":1580058997}
