{"gender":"Male","age":24,"nationality":"IN","familiarity":"Everyday","englishLevel":"Intermediate","dominantHand":"Right","swipeHand":"Right","swipeFinger":"Thumb","screenWidth":360,"screenHeight":640,"devicePixelRatio":3,"maxTouchPoints":5,"platform":"Linux armv7l","vendor":"Google Inc.","referal":"https://www.typingtest.com/result.html?acc=66&nwpm=12&gwpm=19&ncpm=64&gcpm=98&dur=180&time=99&chksum=4237&unit=wpm&kh=998&td=null&err=11&hits=162&textfile=oz.txt","language":"en-IN,en-GB;q=0.9,en-US;q=0.8,en;q=0.7,hi;q=0.6","userAgent":"Mozilla/5.0 (Linux; Android 8.1.0; Moto G (5) Plus) AppleWebKit/537.36 (KHTML, like Gecko) Chrome/80.0.3987.119 Mobile Safari/537.36","timestamp":1583251442}
