{"gender":"Female","age":18,"nationality":"GB","familiarity":"Often","englishLevel":"Native","dominantHand":"Right","swipeHand":"Both","swipeFinger":"Thumb","screenWidth":377,"screenHeight":753,"devicePixelRatio":1274999976158142,"maxTouchPoints":2,"platform":"Linux armv7l","vendor":"Google Inc.","referal":"https://www.typingtest.com/result.html?acc=84&nwpm=43&gwpm=51&ncpm=215&gcpm=255&dur=60&time=60&chksum=18073&unit=wpm&kh=998&td=null&err=8&hits=255&textfile=words.txt","language":"en-GB,en-US;q=0.9,en;q=0.8","userAgent":"Mozilla/5.0 (Linux; Android 8.1.0; Archos Access 50S 4G) AppleWebKit/537.36 (KHTML, like Gecko) Chrome/79.0.3945.93 Mobile Safari/537.36","timestamp":1581068483}
